coronatank/__init__.py
coronatank/client.py
coronatank/command.py
coronatank/config.py
coronatank/game.py
coronatank/resources.py
coronatank/server.py
coronatank-0.1.0.dist-info/LICENSE
coronatank-0.1.0.dist-info/WHEEL
coronatank-0.1.0.dist-info/METADATA
coronatank-0.1.0.dist-info/RECORD
