Metadata-Version: 2.1
Name: coronatank
Version: 0.1.0
Summary: A small tank game based on pygame.
Author: Sylvain Roy
Author-email: sylvain.roy@m4x.org
Requires-Python: >=3.7.7,<4.0.0
Classifier: Programming Language :: Python :: 3
Classifier: Programming Language :: Python :: 3.8
Requires-Dist: pygame (>=1.9.6,<2.0.0)
